mactidy/__init__.py
mactidy/__main__.py
mactidy/main.py
mactidy-0.1.0.dist-info/WHEEL
mactidy-0.1.0.dist-info/METADATA
mactidy-0.1.0.dist-info/RECORD
