Metadata-Version: 2.1
Name: mactidy
Version: 0.1.0
Summary: 
Author: NhimHB
Author-email: chienvq@outlook.com
Requires-Python: >=3.9,<4.0
Classifier: Programming Language :: Python :: 3
Classifier: Programming Language :: Python :: 3.10
Classifier: Programming Language :: Python :: 3.9
Requires-Dist: Send2Trash (>=1.8.0,<2.0.0)
Requires-Dist: configparser (>=5.1.0,<6.0.0)
Requires-Dist: pandas (>=1.3.4,<2.0.0)
